{"cameraMode":{"drawMode":0,"name":"Shaded","section":"Shading Mode"},"sceneLighting":true,"audioPlay":false,"sceneViewState":{"m_AlwaysRefresh":false,"showFog":true,"showSkybox":true,"showFlares":true,"showImageEffects":true,"showParticleSystems":true,"showVisualEffectGraphs":true,"m_FxEnabled":true},"in2DMode":false,"pivot":{"x":-13.447339057922364,"y":0.5439236164093018,"z":1.9890025854110718},"rotation":{"x":-0.10017077624797821,"y":0.7228991985321045,"z":-0.10726696252822876,"w":-0.6750709414482117},"size":2.9259450435638429,"orthographic":false}